.gitignore
CHANGES.rst
COPYRIGHT.txt
LICENSE.txt
MANIFEST.in
README.rst
setup.py
zope2.sessioncookie-meta.zcml
docs/Makefile
docs/conf.py
docs/index.rst
zope2/__init__.py
zope2.sessioncookie.egg-info/PKG-INFO
zope2.sessioncookie.egg-info/SOURCES.txt
zope2.sessioncookie.egg-info/dependency_links.txt
zope2.sessioncookie.egg-info/namespace_packages.txt
zope2.sessioncookie.egg-info/requires.txt
zope2.sessioncookie.egg-info/top_level.txt
zope2/sessioncookie/__init__.py
zope2/sessioncookie/config.py
zope2/sessioncookie/interfaces.py
zope2/sessioncookie/meta.zcml
zope2/sessioncookie/zcml.py
zope2/sessioncookie/scripts/__init__.py
zope2/sessioncookie/scripts/install.py
zope2/sessioncookie/scripts/uninstall.py
zope2/sessioncookie/tests/__init__.py
zope2/sessioncookie/tests/test___init__.py
zope2/sessioncookie/tests/test_config.py
zope2/sessioncookie/tests/test_zcml.py