Metadata-Version: 1.1
Name: zope2.sessioncookie
Version: 0.8
Summary: Allow use of Pyramid-style signed or encrypted cookie for scallable Zope2 session storage
Home-page: https://github.com/zopefoundation/zope2.sessioncookie
Author: Tres Seaver, Agendaless Consulting
Author-email: tseaver@agendaless.com
License: ZPL 2.1
Platform: UNKNOWN
Classifier: Development Status :: 3 - Alpha
Classifier: Framework :: Zope2
Classifier: Intended Audience :: Developers
Classifier: License :: OSI Approved :: Zope Public License
Classifier: Operating System :: OS Independent
Classifier: Programming Language :: Python
Classifier: Programming Language :: Python :: 2
Classifier: Programming Language :: Python :: 2.6
Classifier: Programming Language :: Python :: 2.7
Classifier: Programming Language :: Python :: Implementation :: CPython
Classifier: Topic :: Internet :: WWW/HTTP :: Session
Classifier: Topic :: Security :: Cryptography
Classifier: Topic :: Software Development :: Libraries :: Python Modules
